Metadata-Version: 1.0
Name: GaussBinomDist
Version: 0.1
Summary: Gaussian and Binomial distributions
Home-page: UNKNOWN
Author: Generic
Author-email: UNKNOWN
License: UNKNOWN
Platform: UNKNOWN
